city_of_saskatoon_smart_util/__init__.py
city_of_saskatoon_smart_util/smart_util.py
city_of_saskatoon_smart_util/utils.py
city_of_saskatoon_smart_util-0.0.2.dist-info/METADATA
city_of_saskatoon_smart_util-0.0.2.dist-info/WHEEL
city_of_saskatoon_smart_util-0.0.2.dist-info/licenses/LICENSE
city_of_saskatoon_smart_util-0.0.2.dist-info/RECORD
