Metadata-Version: 2.1
Name: city_of_saskatoon_smart_util
Version: 0.0.2
Summary: An unofficial Python module for interacting with the City of Saskatoon's SmartUtil service
Project-URL: Homepage, https://github.com/evansalter/city-of-saskatoon-smart-util
Project-URL: Bug Tracker, https://github.com/evansalter/city-of-saskatoon-smart-util/issues
Author-email: Evan Salter <hi@evansalter.com>
License: MIT License
License-File: LICENSE
Classifier: License :: OSI Approved :: MIT License
Classifier: Operating System :: OS Independent
Classifier: Programming Language :: Python :: 3
Requires-Python: >=3.7
Requires-Dist: city-of-saskatoon-auth>=0.0.3
